{
  "version": "5",
  "dialect": "mysql",
  "id": "f0f3715e-9c72-4698-abb3-62409de8e071",
  "prevId": "ee765c35-c0b8-40ce-9ad2-e74c692d53fd",
  "tables": {
    "Account": {
      "name": "Account",
      "columns": {
        "id": {
          "name": "id",
          "type": "varchar(36)",
          "primaryKey": false,
          "notNull": true,
          "autoincrement": false
        },
        "accountId": {
          "name": "accountId",
          "type": "tinytext",
          "primaryKey": false,
          "notNull": true,
          "autoincrement": false
        },
        "providerId": {
          "name": "providerId",
          "type": "tinytext",
          "primaryKey": false,
          "notNull": true,
          "autoincrement": false
        },
        "user_id": {
          "name": "user_id",
          "type": "varchar(36)",
          "primaryKey": false,
          "notNull": true,
          "autoincrement": false
        },
        "accessToken": {
          "name": "accessToken",
          "type": "mediumtext",
          "primaryKey": false,
          "notNull": false,
          "autoincrement": false
        },
        "refreshToken": {
          "name": "refreshToken",
          "type": "mediumtext",
          "primaryKey": false,
          "notNull": false,
          "autoincrement": false
        },
        "idToken": {
          "name": "idToken",
          "type": "mediumtext",
          "primaryKey": false,
          "notNull": false,
          "autoincrement": false
        },
        "accessTokenExpiresAt": {
          "name": "accessTokenExpiresAt",
          "type": "datetime",
          "primaryKey": false,
          "notNull": false,
          "autoincrement": false
        },
        "refreshTokenExpiresAt": {
          "name": "refreshTokenExpiresAt",
          "type": "datetime",
          "primaryKey": false,
          "notNull": false,
          "autoincrement": false
        },
        "scope": {
          "name": "scope",
          "type": "tinytext",
          "primaryKey": false,
          "notNull": false,
          "autoincrement": false
        },
        "password": {
          "name": "password",
          "type": "tinytext",
          "primaryKey": false,
          "notNull": false,
          "autoincrement": false
        },
        "createdAt": {
          "name": "createdAt",
          "type": "datetime",
          "primaryKey": false,
          "notNull": true,
          "autoincrement": false
        },
        "updatedAt": {
          "name": "updatedAt",
          "type": "datetime",
          "primaryKey": false,
          "notNull": true,
          "autoincrement": false
        }
      },
      "indexes": {
        "fk_account_user1_idx": {
          "name": "fk_account_user1_idx",
          "columns": ["user_id"],
          "isUnique": false
        }
      },
      "foreignKeys": {
        "fk_account_user1": {
          "name": "fk_account_user1",
          "tableFrom": "Account",
          "tableTo": "User",
          "columnsFrom": ["user_id"],
          "columnsTo": ["id"],
          "onDelete": "cascade",
          "onUpdate": "no action"
        }
      },
      "compositePrimaryKeys": {
        "Account_id": {
          "name": "Account_id",
          "columns": ["id"]
        }
      },
      "uniqueConstraints": {},
      "checkConstraint": {}
    },
    "Answer": {
      "name": "Answer",
      "columns": {
        "id": {
          "name": "id",
          "type": "varchar(36)",
          "primaryKey": false,
          "notNull": true,
          "autoincrement": false
        },
        "answer": {
          "name": "answer",
          "type": "mediumtext",
          "primaryKey": false,
          "notNull": true,
          "autoincrement": false
        },
        "correct": {
          "name": "correct",
          "type": "tinyint",
          "primaryKey": false,
          "notNull": false,
          "autoincrement": false
        },
        "position": {
          "name": "position",
          "type": "int",
          "primaryKey": false,
          "notNull": false,
          "autoincrement": false
        },
        "createdAt": {
          "name": "createdAt",
          "type": "datetime",
          "primaryKey": false,
          "notNull": true,
          "autoincrement": false,
          "default": "CURRENT_TIMESTAMP"
        },
        "updatedAt": {
          "name": "updatedAt",
          "type": "datetime",
          "primaryKey": false,
          "notNull": true,
          "autoincrement": false,
          "default": "CURRENT_TIMESTAMP"
        },
        "Question_id": {
          "name": "Question_id",
          "type": "varchar(36)",
          "primaryKey": false,
          "notNull": true,
          "autoincrement": false
        }
      },
      "indexes": {
        "fk_Answer_Question1_idx": {
          "name": "fk_Answer_Question1_idx",
          "columns": ["Question_id"],
          "isUnique": false
        }
      },
      "foreignKeys": {
        "fk_Answer_Question1": {
          "name": "fk_Answer_Question1",
          "tableFrom": "Answer",
          "tableTo": "Question",
          "columnsFrom": ["Question_id"],
          "columnsTo": ["id"],
          "onDelete": "cascade",
          "onUpdate": "no action"
        }
      },
      "compositePrimaryKeys": {
        "Answer_id": {
          "name": "Answer_id",
          "columns": ["id"]
        }
      },
      "uniqueConstraints": {},
      "checkConstraint": {}
    },
    "Category": {
      "name": "Category",
      "columns": {
        "id": {
          "name": "id",
          "type": "varchar(36)",
          "primaryKey": false,
          "notNull": true,
          "autoincrement": false
        },
        "name": {
          "name": "name",
          "type": "tinytext",
          "primaryKey": false,
          "notNull": true,
          "autoincrement": false
        },
        "createdAt": {
          "name": "createdAt",
          "type": "datetime",
          "primaryKey": false,
          "notNull": true,
          "autoincrement": false,
          "default": "CURRENT_TIMESTAMP"
        },
        "updatedAt": {
          "name": "updatedAt",
          "type": "datetime",
          "primaryKey": false,
          "notNull": true,
          "autoincrement": false,
          "default": "CURRENT_TIMESTAMP"
        },
        "prequisite_category_id": {
          "name": "prequisite_category_id",
          "type": "varchar(36)",
          "primaryKey": false,
          "notNull": false,
          "autoincrement": false
        }
      },
      "indexes": {
        "fk_Category_Category1_idx": {
          "name": "fk_Category_Category1_idx",
          "columns": ["prequisite_category_id"],
          "isUnique": false
        }
      },
      "foreignKeys": {
        "fk_Category_Category1": {
          "name": "fk_Category_Category1",
          "tableFrom": "Category",
          "tableTo": "Category",
          "columnsFrom": ["prequisite_category_id"],
          "columnsTo": ["id"],
          "onDelete": "set null",
          "onUpdate": "no action"
        }
      },
      "compositePrimaryKeys": {
        "Category_id": {
          "name": "Category_id",
          "columns": ["id"]
        }
      },
      "uniqueConstraints": {},
      "checkConstraint": {}
    },
    "KnowledgeCheck": {
      "name": "KnowledgeCheck",
      "columns": {
        "id": {
          "name": "id",
          "type": "varchar(36)",
          "primaryKey": false,
          "notNull": true,
          "autoincrement": false
        },
        "name": {
          "name": "name",
          "type": "tinytext",
          "primaryKey": false,
          "notNull": true,
          "autoincrement": false
        },
        "description": {
          "name": "description",
          "type": "mediumtext",
          "primaryKey": false,
          "notNull": false,
          "autoincrement": false
        },
        "owner_id": {
          "name": "owner_id",
          "type": "varchar(36)",
          "primaryKey": false,
          "notNull": true,
          "autoincrement": false
        },
        "public_token": {
          "name": "public_token",
          "type": "varchar(50)",
          "primaryKey": false,
          "notNull": false,
          "autoincrement": false
        },
        "openDate": {
          "name": "openDate",
          "type": "datetime",
          "primaryKey": false,
          "notNull": true,
          "autoincrement": false
        },
        "closeDate": {
          "name": "closeDate",
          "type": "datetime",
          "primaryKey": false,
          "notNull": false,
          "autoincrement": false
        },
        "difficulty": {
          "name": "difficulty",
          "type": "int",
          "primaryKey": false,
          "notNull": true,
          "autoincrement": false
        },
        "createdAt": {
          "name": "createdAt",
          "type": "datetime",
          "primaryKey": false,
          "notNull": true,
          "autoincrement": false,
          "default": "CURRENT_TIMESTAMP"
        },
        "updatedAt": {
          "name": "updatedAt",
          "type": "datetime",
          "primaryKey": false,
          "notNull": true,
          "autoincrement": false,
          "default": "CURRENT_TIMESTAMP"
        },
        "expiresAt": {
          "name": "expiresAt",
          "type": "datetime",
          "primaryKey": false,
          "notNull": false,
          "autoincrement": false,
          "default": "NULL"
        }
      },
      "indexes": {
        "fk_KnowledgeCheck_user1_idx": {
          "name": "fk_KnowledgeCheck_user1_idx",
          "columns": ["owner_id"],
          "isUnique": false
        }
      },
      "foreignKeys": {
        "fk_KnowledgeCheck_user1": {
          "name": "fk_KnowledgeCheck_user1",
          "tableFrom": "KnowledgeCheck",
          "tableTo": "User",
          "columnsFrom": ["owner_id"],
          "columnsTo": ["id"],
          "onDelete": "cascade",
          "onUpdate": "no action"
        }
      },
      "compositePrimaryKeys": {
        "KnowledgeCheck_id": {
          "name": "KnowledgeCheck_id",
          "columns": ["id"]
        }
      },
      "uniqueConstraints": {
        "KnowledgeCheck_public_token_unique": {
          "name": "KnowledgeCheck_public_token_unique",
          "columns": ["public_token"]
        }
      },
      "checkConstraint": {}
    },
    "KnowledgeCheck_Settings": {
      "name": "KnowledgeCheck_Settings",
      "columns": {
        "id": {
          "name": "id",
          "type": "varchar(36)",
          "primaryKey": false,
          "notNull": true,
          "autoincrement": false
        },
        "knowledgecheck_id": {
          "name": "knowledgecheck_id",
          "type": "varchar(36)",
          "primaryKey": false,
          "notNull": true,
          "autoincrement": false
        },
        "allow_anonymous": {
          "name": "allow_anonymous",
          "type": "tinyint",
          "primaryKey": false,
          "notNull": false,
          "autoincrement": false,
          "default": 1
        },
        "randomize_questions": {
          "name": "randomize_questions",
          "type": "tinyint",
          "primaryKey": false,
          "notNull": false,
          "autoincrement": false,
          "default": 1
        },
        "allow_free_navigation": {
          "name": "allow_free_navigation",
          "type": "tinyint",
          "primaryKey": false,
          "notNull": false,
          "autoincrement": false,
          "default": 1
        }
      },
      "indexes": {
        "fk_KnowledgeCheck_Settings_KnowledgeCheck1_idx": {
          "name": "fk_KnowledgeCheck_Settings_KnowledgeCheck1_idx",
          "columns": ["knowledgecheck_id"],
          "isUnique": false
        }
      },
      "foreignKeys": {
        "fk_KnowledgeCheck_Settings_KnowledgeCheck1": {
          "name": "fk_KnowledgeCheck_Settings_KnowledgeCheck1",
          "tableFrom": "KnowledgeCheck_Settings",
          "tableTo": "KnowledgeCheck",
          "columnsFrom": ["knowledgecheck_id"],
          "columnsTo": ["id"],
          "onDelete": "cascade",
          "onUpdate": "no action"
        }
      },
      "compositePrimaryKeys": {
        "KnowledgeCheck_Settings_id": {
          "name": "KnowledgeCheck_Settings_id",
          "columns": ["id"]
        }
      },
      "uniqueConstraints": {},
      "checkConstraint": {}
    },
    "Question": {
      "name": "Question",
      "columns": {
        "id": {
          "name": "id",
          "type": "varchar(36)",
          "primaryKey": false,
          "notNull": true,
          "autoincrement": false
        },
        "type": {
          "name": "type",
          "type": "enum('single-choice','multiple-choice','open-question','drag-drop')",
          "primaryKey": false,
          "notNull": true,
          "autoincrement": false
        },
        "question": {
          "name": "question",
          "type": "mediumtext",
          "primaryKey": false,
          "notNull": true,
          "autoincrement": false
        },
        "points": {
          "name": "points",
          "type": "int",
          "primaryKey": false,
          "notNull": true,
          "autoincrement": false
        },
        "createdAt": {
          "name": "createdAt",
          "type": "datetime",
          "primaryKey": false,
          "notNull": true,
          "autoincrement": false,
          "default": "CURRENT_TIMESTAMP"
        },
        "updatedAt": {
          "name": "updatedAt",
          "type": "datetime",
          "primaryKey": false,
          "notNull": true,
          "autoincrement": false,
          "default": "CURRENT_TIMESTAMP"
        },
        "category_id": {
          "name": "category_id",
          "type": "varchar(36)",
          "primaryKey": false,
          "notNull": true,
          "autoincrement": false
        },
        "knowledgecheck_id": {
          "name": "knowledgecheck_id",
          "type": "varchar(36)",
          "primaryKey": false,
          "notNull": true,
          "autoincrement": false
        }
      },
      "indexes": {
        "fk_Question_Category1_idx": {
          "name": "fk_Question_Category1_idx",
          "columns": ["category_id"],
          "isUnique": false
        },
        "fk_Question_KnowledgeCheck1_idx": {
          "name": "fk_Question_KnowledgeCheck1_idx",
          "columns": ["knowledgecheck_id"],
          "isUnique": false
        }
      },
      "foreignKeys": {
        "fk_Question_Category1": {
          "name": "fk_Question_Category1",
          "tableFrom": "Question",
          "tableTo": "Category",
          "columnsFrom": ["category_id"],
          "columnsTo": ["id"],
          "onDelete": "cascade",
          "onUpdate": "no action"
        },
        "fk_Question_KnowledgeCheck1": {
          "name": "fk_Question_KnowledgeCheck1",
          "tableFrom": "Question",
          "tableTo": "KnowledgeCheck",
          "columnsFrom": ["knowledgecheck_id"],
          "columnsTo": ["id"],
          "onDelete": "cascade",
          "onUpdate": "no action"
        }
      },
      "compositePrimaryKeys": {
        "Question_id": {
          "name": "Question_id",
          "columns": ["id"]
        }
      },
      "uniqueConstraints": {},
      "checkConstraint": {}
    },
    "Session": {
      "name": "Session",
      "columns": {
        "id": {
          "name": "id",
          "type": "varchar(36)",
          "primaryKey": false,
          "notNull": true,
          "autoincrement": false
        },
        "token": {
          "name": "token",
          "type": "tinytext",
          "primaryKey": false,
          "notNull": true,
          "autoincrement": false
        },
        "createdAt": {
          "name": "createdAt",
          "type": "datetime",
          "primaryKey": false,
          "notNull": true,
          "autoincrement": false
        },
        "updatedAt": {
          "name": "updatedAt",
          "type": "datetime",
          "primaryKey": false,
          "notNull": true,
          "autoincrement": false
        },
        "expiresAt": {
          "name": "expiresAt",
          "type": "datetime",
          "primaryKey": false,
          "notNull": true,
          "autoincrement": false
        },
        "ipAddress": {
          "name": "ipAddress",
          "type": "tinytext",
          "primaryKey": false,
          "notNull": false,
          "autoincrement": false
        },
        "userAgent": {
          "name": "userAgent",
          "type": "tinytext",
          "primaryKey": false,
          "notNull": false,
          "autoincrement": false
        },
        "user_id": {
          "name": "user_id",
          "type": "varchar(36)",
          "primaryKey": false,
          "notNull": true,
          "autoincrement": false
        }
      },
      "indexes": {
        "fk_session_user_idx": {
          "name": "fk_session_user_idx",
          "columns": ["user_id"],
          "isUnique": false
        }
      },
      "foreignKeys": {
        "fk_session_user": {
          "name": "fk_session_user",
          "tableFrom": "Session",
          "tableTo": "User",
          "columnsFrom": ["user_id"],
          "columnsTo": ["id"],
          "onDelete": "cascade",
          "onUpdate": "no action"
        }
      },
      "compositePrimaryKeys": {
        "Session_id": {
          "name": "Session_id",
          "columns": ["id"]
        }
      },
      "uniqueConstraints": {},
      "checkConstraint": {}
    },
    "User": {
      "name": "User",
      "columns": {
        "id": {
          "name": "id",
          "type": "varchar(36)",
          "primaryKey": false,
          "notNull": true,
          "autoincrement": false
        },
        "name": {
          "name": "name",
          "type": "tinytext",
          "primaryKey": false,
          "notNull": true,
          "autoincrement": false
        },
        "email": {
          "name": "email",
          "type": "tinytext",
          "primaryKey": false,
          "notNull": true,
          "autoincrement": false
        },
        "emailVerified": {
          "name": "emailVerified",
          "type": "tinyint",
          "primaryKey": false,
          "notNull": true,
          "autoincrement": false
        },
        "image": {
          "name": "image",
          "type": "varchar(512)",
          "primaryKey": false,
          "notNull": false,
          "autoincrement": false
        },
        "createdAt": {
          "name": "createdAt",
          "type": "datetime",
          "primaryKey": false,
          "notNull": true,
          "autoincrement": false
        },
        "updatedAt": {
          "name": "updatedAt",
          "type": "datetime",
          "primaryKey": false,
          "notNull": true,
          "autoincrement": false
        },
        "isAnonymous": {
          "name": "isAnonymous",
          "type": "boolean",
          "primaryKey": false,
          "notNull": false,
          "autoincrement": false
        }
      },
      "indexes": {},
      "foreignKeys": {},
      "compositePrimaryKeys": {
        "User_id": {
          "name": "User_id",
          "columns": ["id"]
        }
      },
      "uniqueConstraints": {},
      "checkConstraint": {}
    },
    "User_contributesTo_KnowledgeCheck": {
      "name": "User_contributesTo_KnowledgeCheck",
      "columns": {
        "user_id": {
          "name": "user_id",
          "type": "varchar(36)",
          "primaryKey": false,
          "notNull": true,
          "autoincrement": false
        },
        "knowledgecheck_id": {
          "name": "knowledgecheck_id",
          "type": "varchar(36)",
          "primaryKey": false,
          "notNull": true,
          "autoincrement": false
        }
      },
      "indexes": {
        "fk_user_has_KnowledgeCheck_KnowledgeCheck1_idx": {
          "name": "fk_user_has_KnowledgeCheck_KnowledgeCheck1_idx",
          "columns": ["knowledgecheck_id"],
          "isUnique": false
        },
        "fk_user_has_KnowledgeCheck_user1_idx": {
          "name": "fk_user_has_KnowledgeCheck_user1_idx",
          "columns": ["user_id"],
          "isUnique": false
        }
      },
      "foreignKeys": {
        "fk_user_has_KnowledgeCheck_user1": {
          "name": "fk_user_has_KnowledgeCheck_user1",
          "tableFrom": "User_contributesTo_KnowledgeCheck",
          "tableTo": "User",
          "columnsFrom": ["user_id"],
          "columnsTo": ["id"],
          "onDelete": "cascade",
          "onUpdate": "cascade"
        },
        "fk_user_has_KnowledgeCheck_KnowledgeCheck1": {
          "name": "fk_user_has_KnowledgeCheck_KnowledgeCheck1",
          "tableFrom": "User_contributesTo_KnowledgeCheck",
          "tableTo": "KnowledgeCheck",
          "columnsFrom": ["knowledgecheck_id"],
          "columnsTo": ["id"],
          "onDelete": "cascade",
          "onUpdate": "no action"
        }
      },
      "compositePrimaryKeys": {
        "User_has_done_KnowledgeCheck_pk": {
          "name": "User_has_done_KnowledgeCheck_pk",
          "columns": ["user_id", "knowledgecheck_id"]
        }
      },
      "uniqueConstraints": {},
      "checkConstraint": {}
    },
    "User_has_done_KnowledgeCheck": {
      "name": "User_has_done_KnowledgeCheck",
      "columns": {
        "id": {
          "name": "id",
          "type": "int",
          "primaryKey": false,
          "notNull": true,
          "autoincrement": true
        },
        "user_id": {
          "name": "user_id",
          "type": "varchar(36)",
          "primaryKey": false,
          "notNull": true,
          "autoincrement": false
        },
        "knowledgeCheck_id": {
          "name": "knowledgeCheck_id",
          "type": "varchar(36)",
          "primaryKey": false,
          "notNull": true,
          "autoincrement": false
        },
        "startedAt": {
          "name": "startedAt",
          "type": "datetime",
          "primaryKey": false,
          "notNull": true,
          "autoincrement": false
        },
        "finishedAt": {
          "name": "finishedAt",
          "type": "datetime",
          "primaryKey": false,
          "notNull": true,
          "autoincrement": false
        },
        "score": {
          "name": "score",
          "type": "int",
          "primaryKey": false,
          "notNull": true,
          "autoincrement": false
        },
        "results": {
          "name": "results",
          "type": "json",
          "primaryKey": false,
          "notNull": true,
          "autoincrement": false
        }
      },
      "indexes": {
        "fk_user_has_KnowledgeCheck_KnowledgeCheck2_idx": {
          "name": "fk_user_has_KnowledgeCheck_KnowledgeCheck2_idx",
          "columns": ["knowledgeCheck_id"],
          "isUnique": false
        },
        "fk_user_has_KnowledgeCheck_user2_idx": {
          "name": "fk_user_has_KnowledgeCheck_user2_idx",
          "columns": ["user_id"],
          "isUnique": false
        }
      },
      "foreignKeys": {
        "fk_user_has_KnowledgeCheck_user2": {
          "name": "fk_user_has_KnowledgeCheck_user2",
          "tableFrom": "User_has_done_KnowledgeCheck",
          "tableTo": "User",
          "columnsFrom": ["user_id"],
          "columnsTo": ["id"],
          "onDelete": "cascade",
          "onUpdate": "no action"
        },
        "fk_user_has_KnowledgeCheck_KnowledgeCheck2": {
          "name": "fk_user_has_KnowledgeCheck_KnowledgeCheck2",
          "tableFrom": "User_has_done_KnowledgeCheck",
          "tableTo": "KnowledgeCheck",
          "columnsFrom": ["knowledgeCheck_id"],
          "columnsTo": ["id"],
          "onDelete": "cascade",
          "onUpdate": "no action"
        }
      },
      "compositePrimaryKeys": {
        "User_has_done_KnowledgeCheck_id_user_id_knowledgeCheck_id_pk": {
          "name": "User_has_done_KnowledgeCheck_id_user_id_knowledgeCheck_id_pk",
          "columns": ["id", "user_id", "knowledgeCheck_id"]
        }
      },
      "uniqueConstraints": {},
      "checkConstraint": {}
    },
    "Verification": {
      "name": "Verification",
      "columns": {
        "id": {
          "name": "id",
          "type": "varchar(36)",
          "primaryKey": false,
          "notNull": true,
          "autoincrement": false
        },
        "identifier": {
          "name": "identifier",
          "type": "tinytext",
          "primaryKey": false,
          "notNull": true,
          "autoincrement": false
        },
        "value": {
          "name": "value",
          "type": "varchar(1024)",
          "primaryKey": false,
          "notNull": true,
          "autoincrement": false
        },
        "expiresAt": {
          "name": "expiresAt",
          "type": "datetime",
          "primaryKey": false,
          "notNull": true,
          "autoincrement": false
        },
        "createdAt": {
          "name": "createdAt",
          "type": "datetime",
          "primaryKey": false,
          "notNull": true,
          "autoincrement": false
        },
        "updatedAt": {
          "name": "updatedAt",
          "type": "datetime",
          "primaryKey": false,
          "notNull": true,
          "autoincrement": false
        }
      },
      "indexes": {},
      "foreignKeys": {},
      "compositePrimaryKeys": {
        "Verification_id": {
          "name": "Verification_id",
          "columns": ["id"]
        }
      },
      "uniqueConstraints": {},
      "checkConstraint": {}
    }
  },
  "views": {},
  "_meta": {
    "schemas": {},
    "tables": {},
    "columns": {}
  },
  "internal": {
    "tables": {},
    "indexes": {}
  }
}
